{
  "reddit_volume": {
    "predictions": [
      {
        "ds": "2026-02-15T00:00:00",
        "yhat": 156.02770542637194,
        "yhat_lower": 67.72802363947676,
        "yhat_upper": 248.16037218462827
      },
      {
        "ds": "2026-02-22T00:00:00",
        "yhat": 157.18172981611008,
        "yhat_lower": 65.91682004319686,
        "yhat_upper": 243.40568349182655
      },
      {
        "ds": "2026-03-01T00:00:00",
        "yhat": 158.33575420584765,
        "yhat_lower": 66.95733697509782,
        "yhat_upper": 245.31816333409395
      },
      {
        "ds": "2026-03-08T00:00:00",
        "yhat": 159.4897785955858,
        "yhat_lower": 77.69843034042049,
        "yhat_upper": 247.18519734163183
      },
      {
        "ds": "2026-03-15T00:00:00",
        "yhat": 160.64380298532362,
        "yhat_lower": 77.35857582317324,
        "yhat_upper": 242.91674373081628
      },
      {
        "ds": "2026-03-22T00:00:00",
        "yhat": 161.7978273750618,
        "yhat_lower": 82.26173766105009,
        "yhat_upper": 248.2401436301407
      },
      {
        "ds": "2026-03-29T00:00:00",
        "yhat": 162.95185176479987,
        "yhat_lower": 78.07542665096378,
        "yhat_upper": 245.12194391990033
      },
      {
        "ds": "2026-04-05T00:00:00",
        "yhat": 164.10587615453773,
        "yhat_lower": 79.8387391154622,
        "yhat_upper": 252.04562222859084
      },
      {
        "ds": "2026-04-12T00:00:00",
        "yhat": 165.25990054427587,
        "yhat_lower": 75.62467162353683,
        "yhat_upper": 254.779671864733
      },
      {
        "ds": "2026-04-19T00:00:00",
        "yhat": 166.41392493401344,
        "yhat_lower": 86.13972278531641,
        "yhat_upper": 255.15640826885883
      },
      {
        "ds": "2026-04-26T00:00:00",
        "yhat": 167.56794932375155,
        "yhat_lower": 82.44315877442476,
        "yhat_upper": 256.37011825909764
      },
      {
        "ds": "2026-05-03T00:00:00",
        "yhat": 168.72197371348955,
        "yhat_lower": 82.02059547961653,
        "yhat_upper": 254.9842053767065
      },
      {
        "ds": "2026-05-10T00:00:00",
        "yhat": 169.87599810322754,
        "yhat_lower": 89.04364066830189,
        "yhat_upper": 250.7198923683511
      }
    ],
    "metrics": {
      "mae": 25.299940412812447,
      "rmse": 44.24540316428443,
      "mape": 422.5153643290737,
      "mdape": 5.586035325146411,
      "coverage": 0.9032258064516129
    },
    "training_weeks": 31,
    "model_type": "Prophet",
    "frequency": "weekly"
  },
  "reddit_sentiment": {
    "predictions": [
      {
        "ds": "2026-02-15T00:00:00",
        "yhat": -0.8910372836054309,
        "yhat_lower": -1.6318424956053557,
        "yhat_upper": -0.06934854492233705
      },
      {
        "ds": "2026-02-22T00:00:00",
        "yhat": -0.9132168864574761,
        "yhat_lower": -1.6505334548815813,
        "yhat_upper": -0.10516264379377432
      },
      {
        "ds": "2026-03-01T00:00:00",
        "yhat": -0.9353964893095186,
        "yhat_lower": -1.6553436574168998,
        "yhat_upper": -0.10338220675121447
      },
      {
        "ds": "2026-03-08T00:00:00",
        "yhat": -0.9575760921615638,
        "yhat_lower": -1.726097625455985,
        "yhat_upper": -0.13930289149537858
      },
      {
        "ds": "2026-03-15T00:00:00",
        "yhat": -0.9797556950136076,
        "yhat_lower": -1.7702708918009693,
        "yhat_upper": -0.1401839194058092
      },
      {
        "ds": "2026-03-22T00:00:00",
        "yhat": -1.0019352978656528,
        "yhat_lower": -1.8118673470874966,
        "yhat_upper": -0.21241751022600044
      },
      {
        "ds": "2026-03-29T00:00:00",
        "yhat": -1.024114900717698,
        "yhat_lower": -1.88741079842361,
        "yhat_upper": -0.25709045486632126
      },
      {
        "ds": "2026-04-05T00:00:00",
        "yhat": -1.0462945035697417,
        "yhat_lower": -1.7974435347454965,
        "yhat_upper": -0.1975636967508207
      },
      {
        "ds": "2026-04-12T00:00:00",
        "yhat": -1.0684741064217869,
        "yhat_lower": -1.8474958037288993,
        "yhat_upper": -0.24568267968018448
      },
      {
        "ds": "2026-04-19T00:00:00",
        "yhat": -1.0906537092738293,
        "yhat_lower": -1.882738332840569,
        "yhat_upper": -0.32048638277385894
      },
      {
        "ds": "2026-04-26T00:00:00",
        "yhat": -1.1128333121258744,
        "yhat_lower": -1.9062154920370817,
        "yhat_upper": -0.37929615186032106
      },
      {
        "ds": "2026-05-03T00:00:00",
        "yhat": -1.135012914977919,
        "yhat_lower": -1.8785879572009883,
        "yhat_upper": -0.335615212891556
      },
      {
        "ds": "2026-05-10T00:00:00",
        "yhat": -1.1571925178299636,
        "yhat_lower": -1.987730838410326,
        "yhat_upper": -0.3629396859914722
      }
    ],
    "metrics": {
      "mae": 0.2715769504376583,
      "rmse": 0.41198788724881114,
      "mape": 49.82838203255795,
      "mdape": 23.634272476004856,
      "coverage": 0.9354838709677419
    },
    "training_weeks": 31,
    "model_type": "Prophet",
    "frequency": "weekly"
  },
  "news_volume": {
    "predictions": [
      {
        "ds": "2026-02-15T00:00:00",
        "yhat": 0.0,
        "yhat_lower": 0.0,
        "yhat_upper": -1.4121128501066076
      },
      {
        "ds": "2026-02-22T00:00:00",
        "yhat": 0.0,
        "yhat_lower": 0.0,
        "yhat_upper": -1.0872296447240206
      },
      {
        "ds": "2026-03-01T00:00:00",
        "yhat": 0.0,
        "yhat_lower": 0.0,
        "yhat_upper": -1.0843386751988466
      },
      {
        "ds": "2026-03-08T00:00:00",
        "yhat": 0.0,
        "yhat_lower": 0.0,
        "yhat_upper": -0.6936669560086053
      },
      {
        "ds": "2026-03-15T00:00:00",
        "yhat": 0.0,
        "yhat_lower": 0.0,
        "yhat_upper": -0.9123986567577993
      },
      {
        "ds": "2026-03-22T00:00:00",
        "yhat": 0.0,
        "yhat_lower": 0.0,
        "yhat_upper": -0.6360502748268644
      },
      {
        "ds": "2026-03-29T00:00:00",
        "yhat": 0.0,
        "yhat_lower": 0.0,
        "yhat_upper": -0.7799780659577255
      },
      {
        "ds": "2026-04-05T00:00:00",
        "yhat": 0.0,
        "yhat_lower": 0.0,
        "yhat_upper": -0.18535654435924473
      },
      {
        "ds": "2026-04-12T00:00:00",
        "yhat": 0.0,
        "yhat_lower": 0.0,
        "yhat_upper": -0.4878885358599105
      },
      {
        "ds": "2026-04-19T00:00:00",
        "yhat": 0.0,
        "yhat_lower": 0.0,
        "yhat_upper": -0.07171914485956365
      },
      {
        "ds": "2026-04-26T00:00:00",
        "yhat": 0.0,
        "yhat_lower": 0.0,
        "yhat_upper": -0.22028533944531195
      },
      {
        "ds": "2026-05-03T00:00:00",
        "yhat": 0.0,
        "yhat_lower": 0.0,
        "yhat_upper": -0.07166340751581211
      },
      {
        "ds": "2026-05-10T00:00:00",
        "yhat": 0.0,
        "yhat_lower": 0.0,
        "yhat_upper": 0.11117403176226827
      }
    ],
    "metrics": {
      "mae": 1.6825920881895549,
      "rmse": 2.1004073561269085,
      "mape": 1.758756403864907,
      "mdape": 1.7021971856952596,
      "coverage": 0.9375
    },
    "training_weeks": 16,
    "model_type": "Prophet",
    "frequency": "weekly"
  },
  "news_sentiment": {
    "predictions": [
      {
        "ds": "2026-02-15T00:00:00",
        "yhat": -0.041529974106992794,
        "yhat_lower": -0.5652350201224173,
        "yhat_upper": 0.4350636647855922
      },
      {
        "ds": "2026-02-22T00:00:00",
        "yhat": -0.04525909349994232,
        "yhat_lower": -0.5180592324498193,
        "yhat_upper": 0.45785881177510074
      },
      {
        "ds": "2026-03-01T00:00:00",
        "yhat": -0.048988212891973006,
        "yhat_lower": -0.576752512381904,
        "yhat_upper": 0.43204836886785675
      },
      {
        "ds": "2026-03-08T00:00:00",
        "yhat": -0.05271733228492252,
        "yhat_lower": -0.5400632107950991,
        "yhat_upper": 0.4499041393966543
      },
      {
        "ds": "2026-03-15T00:00:00",
        "yhat": -0.056446451677429024,
        "yhat_lower": -0.5588124731434645,
        "yhat_upper": 0.4079615966752096
      },
      {
        "ds": "2026-03-22T00:00:00",
        "yhat": -0.06017557107037854,
        "yhat_lower": -0.5136128349046564,
        "yhat_upper": 0.35909448516514464
      },
      {
        "ds": "2026-03-29T00:00:00",
        "yhat": -0.06390469046332806,
        "yhat_lower": -0.5349078519513542,
        "yhat_upper": 0.4114264314513372
      },
      {
        "ds": "2026-04-05T00:00:00",
        "yhat": -0.06763380985583455,
        "yhat_lower": -0.5652569714294402,
        "yhat_upper": 0.36513598122645974
      },
      {
        "ds": "2026-04-12T00:00:00",
        "yhat": -0.0713629292487841,
        "yhat_lower": -0.5762895488930294,
        "yhat_upper": 0.4009873108281558
      },
      {
        "ds": "2026-04-19T00:00:00",
        "yhat": -0.07509204864081478,
        "yhat_lower": -0.5628122436740207,
        "yhat_upper": 0.38053959008583765
      },
      {
        "ds": "2026-04-26T00:00:00",
        "yhat": -0.0788211680337643,
        "yhat_lower": -0.5891469540042766,
        "yhat_upper": 0.4019200425152016
      },
      {
        "ds": "2026-05-03T00:00:00",
        "yhat": -0.08255028742649233,
        "yhat_lower": -0.5521755970559725,
        "yhat_upper": 0.4014361634939977
      },
      {
        "ds": "2026-05-10T00:00:00",
        "yhat": -0.0862794068192203,
        "yhat_lower": -0.5599281507276384,
        "yhat_upper": 0.3902539372774366
      }
    ],
    "metrics": {
      "mae": 0.20236724439444975,
      "rmse": 0.24848155603771682,
      "mape": 81.85105756038406,
      "mdape": 43.370377027117826,
      "coverage": 0.9375
    },
    "training_weeks": 16,
    "model_type": "Prophet",
    "frequency": "weekly"
  },
  "metadata": {
    "forecast_horizon_weeks": 13,
    "training_timestamp": "20260220_180244",
    "prophet_config": {
      "changepoint_prior_scale": 0.05,
      "seasonality_prior_scale": 10.0,
      "seasonality_mode": "additive",
      "weekly_seasonality": true,
      "yearly_seasonality": false,
      "daily_seasonality": false,
      "confidence_interval": 0.95
    },
    "data_sources": {
      "reddit": {
        "date_range": "2025-07-14 to 2026-02-09",
        "weeks": 31
      },
      "news": {
        "date_range": "2025-10-27 to 2026-02-09",
        "weeks": 16
      }
    }
  }
}